stressor_ps.py
stressor_ps-0.0.4.dist-info/LICENSE.txt
stressor_ps-0.0.4.dist-info/METADATA
stressor_ps-0.0.4.dist-info/WHEEL
stressor_ps-0.0.4.dist-info/entry_points.txt
stressor_ps-0.0.4.dist-info/top_level.txt
stressor_ps-0.0.4.dist-info/RECORD
