Metadata-Version: 2.1
Name: stressor-ps
Version: 0.0.4
Summary: Add a 'ps' task to stressor
Home-page: https://github.com/mar10/stressor-ps/
Author: Martin Wendt
Author-email: stressor@wwwendt.de
Maintainer: Martin Wendt
Maintainer-email: stressor@wwwendt.de
License: MIT
Keywords: stressor,stressor-plugin
Platform: UNKNOWN
Classifier: Development Status :: 3 - Alpha
Classifier: Environment :: Console
Classifier: Intended Audience :: Developers
Classifier: License :: OSI Approved :: MIT License
Classifier: Operating System :: OS Independent
Classifier: Programming Language :: Python
Classifier: Programming Language :: Python :: 3
Classifier: Programming Language :: Python :: 3.5
Classifier: Programming Language :: Python :: 3.6
Classifier: Programming Language :: Python :: 3.7
Classifier: Programming Language :: Python :: 3.8
Classifier: Topic :: Software Development :: Libraries :: Python Modules
Classifier: Topic :: Software Development :: Quality Assurance
Classifier: Topic :: Software Development :: Testing
Classifier: Topic :: Software Development :: Testing :: Traffic Generation
